MANIFEST.in
README.md
setup.py
sample/__init__.py
sample/app.py
sample/main.py
test_dev_toml/__init__.py
test_dev_toml.egg-info/PKG-INFO
test_dev_toml.egg-info/SOURCES.txt
test_dev_toml.egg-info/dependency_links.txt
test_dev_toml.egg-info/top_level.txt
test_dev_toml/lib/.gitignore
test_dev_toml/lib/__init__.py
test_dev_toml/lib/build_info.py
test_dev_toml/lib/constants_version.py
test_dev_toml/lib/main.py