Metadata-Version: 2.1
Name: test-dev-toml
Version: 0.0.1
Summary: python module to generate Makefiles for arduino, GTest, /CC++, etc.
Home-page: https://bitbucket.org/arrizza-public/test-dev-toml/src/master
Download-URL: https://bitbucket.org/arrizza-public/test-dev-toml/get/master.zip
Author: J. Arrizza
Author-email: cppgent0@gmail.com
License: MIT
Keywords: makefile,generation,python
Classifier: Development Status :: 2 - Pre-Alpha
Classifier: Environment :: Console
Classifier: Intended Audience :: Developers
Classifier: Topic :: Utilities
Classifier: Programming Language :: Python :: 3.9
Classifier: License :: OSI Approved :: MIT License
